odoo8_addon_web_listview_custom_element_number-8.0.1.0.0.99.dev10-py2.7-nspkg.pth
odoo8_addon_web_listview_custom_element_number-8.0.1.0.0.99.dev10.dist-info/DESCRIPTION.rst
odoo8_addon_web_listview_custom_element_number-8.0.1.0.0.99.dev10.dist-info/METADATA
odoo8_addon_web_listview_custom_element_number-8.0.1.0.0.99.dev10.dist-info/RECORD
odoo8_addon_web_listview_custom_element_number-8.0.1.0.0.99.dev10.dist-info/WHEEL
odoo8_addon_web_listview_custom_element_number-8.0.1.0.0.99.dev10.dist-info/metadata.json
odoo8_addon_web_listview_custom_element_number-8.0.1.0.0.99.dev10.dist-info/namespace_packages.txt
odoo8_addon_web_listview_custom_element_number-8.0.1.0.0.99.dev10.dist-info/top_level.txt
odoo_addons/web_listview_custom_element_number/README.rst
odoo_addons/web_listview_custom_element_number/__init__.py
odoo_addons/web_listview_custom_element_number/__openerp__.py
odoo_addons/web_listview_custom_element_number/i18n/ar.po
odoo_addons/web_listview_custom_element_number/i18n/de.po
odoo_addons/web_listview_custom_element_number/i18n/es.po
odoo_addons/web_listview_custom_element_number/i18n/fi.po
odoo_addons/web_listview_custom_element_number/i18n/fr.po
odoo_addons/web_listview_custom_element_number/i18n/it.po
odoo_addons/web_listview_custom_element_number/i18n/pt_BR.po
odoo_addons/web_listview_custom_element_number/i18n/sl.po
odoo_addons/web_listview_custom_element_number/i18n/tr.po
odoo_addons/web_listview_custom_element_number/i18n/web_listview_custom_element_number.pot
odoo_addons/web_listview_custom_element_number/static/description/icon.png
odoo_addons/web_listview_custom_element_number/static/src/css/web_listview_custom_element_number.css
odoo_addons/web_listview_custom_element_number/static/src/img/screnshot_chrome.png
odoo_addons/web_listview_custom_element_number/static/src/img/screnshot_firefox.png
odoo_addons/web_listview_custom_element_number/static/src/img/screnshot_partner_limit.png
odoo_addons/web_listview_custom_element_number/static/src/js/web_listview_custom_element_number.js
odoo_addons/web_listview_custom_element_number/views/templates.xml
